{"requestURL":"https://t24mobile.com/scripts/controllers/accountsCtrl.js","requestMethod":"GET","requestHeaders":{"Referer":"https://t24mobile.com/","User-Agent":"Mozilla/5.0 (X11; Linux x86_64) AppleWebKit/537.36 (KHTML, like Gecko) Chrome/56.0.2924.76 Safari/537.36"},"responseURL":"https://t24mobile.com/scripts/controllers/accountsCtrl.js","responseStatus":200,"responseStatusText":"OK","responseProtocol":"http/1.1","responseBody":"t24App.controller('accountsCtrl', ['$scope','appService','authService','$log','$cookieStore','$window','$state', function($scope,appService,authService,$log,$cookieStore,$window,$state){\r\n\tconsole.log('accountsCtrl' ,$cookieStore.get('globals').currentUser.registeredID);\r\n\tvar appToken = $cookieStore.get('appToken');\r\n\tvar mobileNo = $cookieStore.get('globals').currentUser.registeredID;\r\n\t$scope.loggedIn = $cookieStore.get('userloggedIn');\r\n\tvar s =  $cookieStore.get('invisible');\r\n    $scope.invisible = s;\r\n\r\n\t$scope.loadCustomerAccount = function(){\r\n\tconsole.log('accountsCtrl' ,$cookieStore.get('globals').currentUser.registeredID);\r\n\r\n\t\t//appService.getProfile(\"8976595947\",\"C1D048FA84B21D197B0AA67A536DD2E49C54321D79A832304BC7403A9E23F3AB791D92BBA038462B\",function(response){\r\n\t\tappService.getProfile($cookieStore.get('globals').currentUser.registeredID,appToken,function(response){\r\n\t\t\tconsole.log(response);\r\n\r\n\r\n\t\t\tappService.getCustomerAcc(response.data.contactNo,response.data.custToken,function(response){\r\n\t\t\t\t$log.info(response);\r\n\t\t\t\tif(response.data != null){\r\n\t\t\t\t$scope.customerAccDetails = response.data['Balance Info : '];\r\n\t\t\t}else if (response.isSuccessful == false && response.msgDesc == 'Token is Not Valid') {\r\n                //$log.log(response.msgDesc);\r\n                if ($scope.loggedIn == 1) {\r\n                    $scope.invisible = !s; //!authService.invisible;\r\n                    $cookieStore.put('invisible', !s);\r\n                    $cookieStore.put('userloggedIn', 0);\r\n                    authService.clearCredentials();\r\n                    $window.alert('Session Expired ! Please login again.');\r\n                    $state.go('home');\r\n\r\n                } else {\r\n                    $window.alert('Session Expired ! Click OK to start session again');\r\n                    $state.go('home');\r\n                }\r\n            }else{\r\n\t\t\t\t$scope.customerAccDetails = 0;\r\n\t\t\t}\r\n\t\t\t\t\r\n\t\t\t\t//$log.info($scope.customerAccDetails);\r\n\t\t\t});\r\n\t\t});\r\n\t};\r\n\r\n\t$scope.loadCustomerAccount();\r\n}]);\r\n","responseBase64":false,"responseHeaders":{"Date":"Fri, 26 May 2017 20:00:28 GMT","Content-Encoding":"gzip","ETag":"\"cc4fc68cda8cd21:0\"","Last-Modified":"Wed, 22 Feb 2017 07:09:03 GMT","Server":"Microsoft-IIS/7.5","X-Powered-By":"ASP.NET","Vary":"Accept-Encoding","Content-Type":"application/x-javascript","Access-Control-Allow-Origin":"*","Accept-Ranges":"bytes","Content-Length":"908"}}